surfio/__init__.py
surfio/_surfio.cp312-win_amd64.pyd
surfio/_surfio.pyi
surfio/py.typed
surfio-0.0.15.dist-info/METADATA
surfio-0.0.15.dist-info/WHEEL
surfio-0.0.15.dist-info/licenses/COPYING
surfio-0.0.15.dist-info/RECORD
